{
  "hash": "6bdca84e",
  "configHash": "029e52ba",
  "lockfileHash": "ad57abcb",
  "browserHash": "83533439",
  "optimized": {
    "vue": {
      "src": "../../../../node_modules/vue/dist/vue.runtime.esm-bundler.js",
      "file": "vue.js",
      "fileHash": "a7da9ce0",
      "needsInterop": false
    },
    "vitepress > @vue/devtools-api": {
      "src": "../../../../node_modules/@vue/devtools-api/dist/index.js",
      "file": "vitepress___@vue_devtools-api.js",
      "fileHash": "b7a6c975",
      "needsInterop": false
    },
    "vitepress > @vueuse/core": {
      "src": "../../../../node_modules/@vueuse/core/index.mjs",
      "file": "vitepress___@vueuse_core.js",
      "fileHash": "45c3c97d",
      "needsInterop": false
    },
    "@theme/index": {
      "src": "../../../../node_modules/vitepress/dist/client/theme-default/index.js",
      "file": "@theme_index.js",
      "fileHash": "5682ca0d",
      "needsInterop": false
    }
  },
  "chunks": {
    "chunk-P2XGSYO7": {
      "file": "chunk-P2XGSYO7.js"
    },
    "chunk-HVR2FF6M": {
      "file": "chunk-HVR2FF6M.js"
    }
  }
}